setup.py
babbage_fiscal/__init__.py
babbage_fiscal/api.py
babbage_fiscal/callbacks.py
babbage_fiscal/celeryconfig.py
babbage_fiscal/cli.py
babbage_fiscal/config.py
babbage_fiscal/db_utils.py
babbage_fiscal/fdp_utils.py
babbage_fiscal/loader.py
babbage_fiscal/model_registry.py
babbage_fiscal/row_processor.py
babbage_fiscal/tasks.py
babbage_fiscal.egg-info/PKG-INFO
babbage_fiscal.egg-info/SOURCES.txt
babbage_fiscal.egg-info/dependency_links.txt
babbage_fiscal.egg-info/entry_points.txt
babbage_fiscal.egg-info/namespace_packages.txt
babbage_fiscal.egg-info/not-zip-safe
babbage_fiscal.egg-info/requires.txt
babbage_fiscal.egg-info/top_level.txt
tests/__init__.py
tests/conftest.py
tests/test_api.py
tests/test_cli.py
tests/test_common.py
tests/test_loader.py
tests/test_registry.py