Metadata-Version: 1.1
Name: babbage-fiscal
Version: 0.0.10
Summary: API and Bi-directional converter babbage/fdp
Home-page: https://github.com/openspending/babbage.fiscal-data-package
Author: OpenSpending
Author-email: info@openspending.org
License: MIT
Keywords: schema jsontableschema jts fdp fiscal data babbage
Platform: UNKNOWN
Classifier: Development Status :: 3 - Alpha
Classifier: Intended Audience :: Developers
Classifier: License :: OSI Approved :: MIT License
Classifier: Operating System :: OS Independent
Classifier: Programming Language :: Python :: 3.3
Classifier: Programming Language :: Python :: 3.4
Classifier: Programming Language :: Python :: 3.5
